tomato_commander/__init__.py
tomato_commander/main.py
tomato_commander/router.py
tomato_commander/tomato_commander.py
tomato_commander-0.1.4.dist-info/DESCRIPTION.rst
tomato_commander-0.1.4.dist-info/METADATA
tomato_commander-0.1.4.dist-info/RECORD
tomato_commander-0.1.4.dist-info/WHEEL
tomato_commander-0.1.4.dist-info/metadata.json
tomato_commander-0.1.4.dist-info/top_level.txt
