Metadata-Version: 2.0
Name: tomato-commander
Version: 0.1.4
Summary: Simple library for controlling static leases on a tomato router.
Home-page: https://github.com/voglster/tomato_commander
Author: James Vogel
Author-email: jim.m.vogel@gmail.com
License: GNU General Public License v3
Keywords: tomato_commander
Platform: UNKNOWN
Classifier: Development Status :: 2 - Pre-Alpha
Classifier: Intended Audience :: Developers
Classifier: License :: OSI Approved :: GNU General Public License v3 (GPLv3)
Classifier: Natural Language :: English
Classifier: Programming Language :: Python :: 3.6
Requires-Dist: fabric3 (==1.13.1.post1)
